adafruit_mlx90614.py
adafruit_circuitpython_mlx90614-1.2.21.dist-info/licenses/LICENSE
adafruit_circuitpython_mlx90614-1.2.21.dist-info/METADATA
adafruit_circuitpython_mlx90614-1.2.21.dist-info/WHEEL
adafruit_circuitpython_mlx90614-1.2.21.dist-info/top_level.txt
adafruit_circuitpython_mlx90614-1.2.21.dist-info/RECORD
